simqclient/__init__.py
simqclient/client.py
simqclient/debug.py
simqclient/exceptions.py
simqclient/service.py
simqclient-0.1.0.dist-info/LICENSE
simqclient-0.1.0.dist-info/METADATA
simqclient-0.1.0.dist-info/WHEEL
simqclient-0.1.0.dist-info/top_level.txt
simqclient-0.1.0.dist-info/RECORD
