Metadata-Version: 2.1
Name: simqclient
Version: 0.1.0
Summary: SIMQ客户端。SIMQ是一款基于redis的消息队列接口服务。
Author: Chen Han
Maintainer: Chen Han
License: Apache License, Version 2.0
Keywords: simq
Classifier: Development Status :: 5 - Production/Stable
Classifier: Intended Audience :: Developers
Classifier: Topic :: Software Development :: Libraries :: Python Modules
Classifier: License :: OSI Approved :: Apache Software License
Classifier: Programming Language :: Python :: 3
Classifier: Programming Language :: Python :: 3 :: Only
License-File: LICENSE
Requires-Dist: requests
